app/__init__.py
app/__main__.py
deploy_actions-0.3.4.dist-info/LICENSE
deploy_actions-0.3.4.dist-info/METADATA
deploy_actions-0.3.4.dist-info/WHEEL
deploy_actions-0.3.4.dist-info/top_level.txt
deploy_actions-0.3.4.dist-info/RECORD
