Metadata-Version: 2.1
Name: deploy-actions
Version: 0.3.4
Summary: Deployable app
Home-page: https://github.com/desty2k/deploy-actions
Author: Wojciech desty2k Wentland
Author-email: wojciech.wentland@int.pl
License: MIT
Project-URL: Issues, https://github.com/desty2k/deploy-actions/issues
Project-URL: Docs, https://desty2k.github.io/deploy-actions/
Platform: UNKNOWN
Requires-Python: >=3.5
